<odoo>
    <data noupdate="1">
        <!--Group for property manager -->
        <record id="group_property_manager" model="res.groups">
            <field name="name">Property Management/ Manager</field>           
        </record>

        <!--Group for property user -->
        <record id="group_property_user" model="res.groups">
            <field name="name">Property Management/ User</field>
        </record>
       <record id="id_properties" model="ir.rule">
            <field name="model_id" ref="model_pms_properties" />
            <field name="name">Property Manager</field>
            <field name="domain_force">[(1,'=',1)]</field>
            <field name="groups" eval="[(4,ref('property_management_system.group_property_manager'))]"/>
        </record>
        <record id="rule_id_properties" model="ir.rule">
            <field name="name">Property User</field>
            <field name="model_id" ref="model_pms_properties"/>
            <field name="domain_force">[('id', 'in', [c.id for c in user.property_id])]</field>    
            <field name="groups" eval="[(4,ref('property_management_system.group_property_user'))]"/>
        </record>
        <record id="id_floor" model="ir.rule">
            <field name="model_id" ref="model_pms_floor" />
            <field name="name">Floor Manager</field>
            <field name="domain_force">[(1,'=',1)]</field>
            <field name="groups" eval="[(4,ref('property_management_system.group_property_manager'))]"/>
        </record>
        <record id="rule_id_floor" model="ir.rule">
            <field name="name">Floor User</field>
            <field name="model_id" ref="model_pms_floor"/>
            <field name="domain_force">[('property_id', 'in', [c.id for c in user.property_id])]</field>    
            <field name="groups" eval="[(4,ref('property_management_system.group_property_user'))]"/>
        </record> 
         <record id="id_space_unit" model="ir.rule">
            <field name="model_id" ref="model_pms_space_unit" />
            <field name="name">Space Unit Manager</field>
            <field name="domain_force">[(1,'=',1)]</field>
            <field name="groups" eval="[(4,ref('property_management_system.group_property_manager'))]"/>
        </record>
        <record id="rule_id_space_unit" model="ir.rule">
            <field name="name">Space Unit User</field>
            <field name="model_id" ref="model_pms_space_unit"/>
            <field name="domain_force">[('property_id', 'in', [c.id for c in user.property_id])]</field>    
            <field name="groups" eval="[(4,ref('property_management_system.group_property_user'))]"/>
        </record>
         <record id="id_lease_agreement" model="ir.rule">
            <field name="model_id" ref="model_pms_lease_agreement" />
            <field name="name">Lease Agreement Manager</field>
            <field name="domain_force">[(1,'=',1)]</field>
            <field name="groups" eval="[(4,ref('property_management_system.group_property_manager'))]"/>
        </record>
        <record id="rule_id_lease_agreement" model="ir.rule">
            <field name="name">Lease Agreement User</field>
            <field name="model_id" ref="model_pms_lease_agreement"/>
            <field name="domain_force">[('property_id', 'in', [c.id for c in user.property_id])]</field>    
            <field name="groups" eval="[(4,ref('property_management_system.group_property_user'))]"/>
        </record>
        <record id="id_facilities" model="ir.rule">
            <field name="model_id" ref="model_pms_facilities" />
            <field name="name">Facilities Manager</field>
            <field name="domain_force">[(1,'=',1)]</field>
            <field name="groups" eval="[(4,ref('property_management_system.group_property_manager'))]"/>
        </record>
        <record id="rule_id_facilities" model="ir.rule">
            <field name="name">Facilities User</field>
            <field name="model_id" ref="model_pms_facilities"/>
            <field name="domain_force">[('property_id', 'in', [c.id for c in user.property_id])]</field>    
            <field name="groups" eval="[(4,ref('property_management_system.group_property_user'))]"/>
        </record>
         <!-- <record id="id_utilities_source_type" model="ir.rule">
            <field name="model_id" ref="model_pms_utilities_source_type" />
            <field name="name">Utilities Source Type Manager</field>
            <field name="domain_force">[(1,'=',1)]</field>
            <field name="groups" eval="[(4,ref('property_management_system.group_property_manager'))]"/>
        </record>
        <record id="rule_id_utilities_source_type" model="ir.rule">
            <field name="name">Utilities Source Type User</field>
            <field name="model_id" ref="model_pms_utilities_source_type"/>
            <field name="domain_force">[('property_id', 'in', [c.id for c in user.property_id])]</field>    
            <field name="groups" eval="[(4,ref('property_management_system.group_property_user'))]"/>
        </record> -->
         <!-- <record id="id_utilities_supply_type" model="ir.rule">
            <field name="model_id" ref="model_pms_utilities_supply_type" />
            <field name="name">Utilities Supply Type Manager</field>
            <field name="domain_force">[(1,'=',1)]</field>
            <field name="groups" eval="[(4,ref('property_management_system.group_property_manager'))]"/>
        </record> -->
        <!-- <record id="rule_id_utilities_supply_type" model="ir.rule">
            <field name="name">Utilities Supply Type User</field>
            <field name="model_id" ref="model_pms_utilities_supply_type"/>
            <field name="domain_force">[('property_id', 'in', [c.id for c in user.property_id])]</field>    
            <field name="groups" eval="[(4,ref('property_management_system.group_property_user'))]"/>
        </record> -->
         <!-- <record id="id_equipment_type" model="ir.rule">
            <field name="model_id" ref="model_pms_equipment_type" />
            <field name="name">Equipment Type Manager</field>
            <field name="domain_force">[(1,'=',1)]</field>
            <field name="groups" eval="[(4,ref('property_management_system.group_property_manager'))]"/>
        </record>
        <record id="rule_id_equipment_type" model="ir.rule">
            <field name="name">Equipment Type User</field>
            <field name="model_id" ref="model_pms_equipment_type"/>
            <field name="domain_force">[('property_id', 'in', [c.id for c in user.property_id])]</field>    
            <field name="groups" eval="[(4,ref('property_management_system.group_property_user'))]"/>
        </record> -->
         <record id="id_equipment" model="ir.rule">
            <field name="model_id" ref="model_pms_equipment" />
            <field name="name">Equipment Manager</field>
            <field name="domain_force">[(1,'=',1)]</field>
            <field name="groups" eval="[(4,ref('property_management_system.group_property_manager'))]"/>
        </record>
        <record id="rule_id_equipment" model="ir.rule">
            <field name="name">Equipment User</field>
            <field name="model_id" ref="model_pms_equipment"/>
            <field name="domain_force">[('property_id', 'in', [c.id for c in user.property_id])]</field>    
            <field name="groups" eval="[(4,ref('property_management_system.group_property_user'))]"/>
        </record>
         <record id="id_facility_lines" model="ir.rule">
            <field name="model_id" ref="model_pms_facility_lines" />
            <field name="name">Facility Lines Manager</field>
            <field name="domain_force">[(1,'=',1)]</field>
            <field name="groups" eval="[(4,ref('property_management_system.group_property_manager'))]"/>
        </record>
        <record id="rule_id_facility_lines" model="ir.rule">
            <field name="name">Facility Lines User</field>
            <field name="model_id" ref="model_pms_facility_lines"/>
            <field name="domain_force">[('property_id', 'in', [c.id for c in user.property_id])]</field>    
            <field name="groups" eval="[(4,ref('property_management_system.group_property_user'))]"/>
        </record>
         <record id="id_pms_rent_schedule" model="ir.rule">
            <field name="model_id" ref="model_pms_rent_schedule"/>
            <field name="name">Rent Schedule Manager</field>
            <field name="domain_force">[(1,'=',1)]</field>
            <field name="groups" eval="[(4,ref('property_management_system.group_property_manager'))]"/>
        </record>
        <record id="rule_pms_rent_schedule" model="ir.rule">
            <field name="name">Rent Schedule User</field>
            <field name="model_id" ref="model_pms_rent_schedule"/>
            <field name="domain_force">[('property_id', 'in', [c.id for c in user.property_id])]</field>    
            <field name="groups" eval="[(4,ref('property_management_system.group_property_user'))]"/>
        </record>
             <record id="id_pms_gen_rent_schedule" model="ir.rule">
            <field name="model_id" ref="model_pms_gen_rent_schedule"/>
            <field name="name">Generated Schedule Manager</field>
            <field name="domain_force">[(1,'=',1)]</field>
            <field name="groups" eval="[(4,ref('property_management_system.group_property_manager'))]"/>
        </record>
        <record id="rule_pms_gen_rent_schedule" model="ir.rule">
            <field name="name">Generated Schedule User</field>
            <field name="model_id" ref="model_pms_gen_rent_schedule"/>
            <field name="domain_force">[('property_id', 'in', [c.id for c in user.property_id])]</field>    
            <field name="groups" eval="[(4,ref('property_management_system.group_property_user'))]"/>
        </record>
         <record id="id_lease_agreement_line" model="ir.rule">
            <field name="model_id" ref="model_pms_lease_agreement_line"/>
            <field name="name">Lease Agreement Line Manager</field>
            <field name="domain_force">[(1,'=',1)]</field>
            <field name="groups" eval="[(4,ref('property_management_system.group_property_manager'))]"/>
        </record>
        <!-- <record id="rule_id_lease_agreement_line" model="ir.rule">
            <field name="name">Lease Agreement Line User</field>
            <field name="model_id" ref="model_pms_lease_agreement_line"/>
            <field name="domain_force">[('property_id', 'in', [c.id for c in user.property_id])]</field>    
            <field name="groups" eval="[(4,ref('property_management_system.group_property_user'))]"/>
        </record> -->
         <!-- <record id="id_rent_schedule" model="ir.rule">
            <field name="model_id" ref="model_pms_rent_schedule"/>                                                                                                                                                                                                                                                                                                                                                                                                                                                                                           />
            <field name="name">Rent Schedule Manager</field>
            <field name="domain_force">[(1,'=',1)]</field>
            <field name="groups" eval="[(4,ref('property_management_system.group_property_manager'))]"/>
        </record> -->
        <!-- <record id="rule_id_rent_schedule" model="ir.rule">
            <field name="name">Rent Schedule User</field>
            <field name="model_id" ref="model_pms_rent_schedule"/>
            <field name="domain_force">[('property_id', 'in', [c.id for c in user.property_id])]</field>    
            <field name="groups" eval="[(4,ref('property_management_system.group_property_user'))]"/>
        </record> -->
    </data>
</odoo>